main.py
valhalla_for_go-0.0.1.dist-info/METADATA
valhalla_for_go-0.0.1.dist-info/WHEEL
valhalla_for_go-0.0.1.dist-info/top_level.txt
valhalla_for_go-0.0.1.dist-info/RECORD
