Metadata-Version: 2.1
Name: valhalla-for-go
Version: 0.0.1
Summary: package two functions locate() and decode_polyline()
Author-email: Yu Peijia <peijia@nextbillion.ai>
Classifier: Programming Language :: Python :: 3
Classifier: License :: OSI Approved :: MIT License
Classifier: Operating System :: OS Independent
Requires-Python: >=3.7
